netunnel/__init__.py
netunnel/client.py
netunnel/common/__init__.py
netunnel/common/auth.py
netunnel/common/channel.py
netunnel/common/const.py
netunnel/common/exceptions.py
netunnel/common/security.py
netunnel/common/tunnel.py
netunnel/common/utils.py
netunnel/server/__init__.py
netunnel/server/__main__.py
netunnel/server/client_handler.py
netunnel/server/config.py
netunnel/server/peer.py
netunnel/server/schemas.py
netunnel/server/server.py
netunnel/server/static_tunnel.py
netunnel-1.0.13.dist-info/LICENSE
netunnel-1.0.13.dist-info/METADATA
netunnel-1.0.13.dist-info/WHEEL
netunnel-1.0.13.dist-info/top_level.txt
netunnel-1.0.13.dist-info/RECORD
