Metadata-Version: 2.1
Name: netunnel
Version: 1.0.13
Summary: A tool to create network tunnels over HTTP/S written in Python 3
Home-page: https://github.com/claroty/netunnel
Author: Claroty Open Source
Author-email: opensource@claroty.com
Maintainer: Claroty Open Source
Maintainer-email: opensource@claroty.com
License: Apache 2
Classifier: Programming Language :: Python
Classifier: Programming Language :: Python :: 3
Classifier: Programming Language :: Python :: 3.6
Classifier: Programming Language :: Python :: 3.7
Classifier: Programming Language :: Python :: 3.8
Classifier: Programming Language :: Python :: 3.9
Classifier: License :: OSI Approved :: Apache Software License
Classifier: Operating System :: OS Independent
Requires-Python: >=3.6
License-File: LICENSE
Requires-Dist: aiohttp<4.0.0,>=3.9.5
Requires-Dist: aiofiles>=0.0.4
Requires-Dist: pymongo>=4.8.0
Requires-Dist: marshmallow<4,>=2.8
Requires-Dist: cryptography>=43.0.0
Requires-Dist: colorama>=0.2
Requires-Dist: click
Requires-Dist: importlib-metadata<4
